lab6-ctrl/controller.v
module controller
(
  input  wire       zero,
  input  wire [2:0] phase,
  input  wire [2:0] opcode,
  output reg        sel,
  output reg        rd,
  output reg        ld_ir,
  output reg        halt,
  output reg        inc_pc,
  output reg        ld_ac,
  output reg        wr,
  output reg        ld_pc,
  output reg        data_e
);

  localparam HLT=0, SKZ=1, ADD=2, AND=3, XOR=4, LDA=5, STO=6, JMP=7;
  localparam INST_ADDR=0, INST_FETCH=1, INST_LOAD=2, IDLE=3, OP_ADDR=4, OP_FETCH=5, ALU_OP=6, STORE=7;

  reg INTER_ALUOP, INTER_HALT, INTER_JMP, INTER_SKZ, INTER_STO;

  always @*
    begin
      INTER_ALUOP = ( opcode == ADD || opcode == AND || opcode == XOR || opcode == LDA );
      INTER_HALT  = ( opcode == HLT );
      INTER_SKZ   = ( opcode == SKZ && zero );
      INTER_JMP   = ( opcode == JMP );
      INTER_STO   = ( opcode == STO );
      case ( phase )
        INST_ADDR  : begin sel=1; rd=0; ld_ir=0; halt=0; inc_pc=0; ld_ac=0; ld_pc=0; wr=0; data_e=0; end
        INST_FETCH : begin sel=1; rd=1; ld_ir=0; halt=0; inc_pc=0; ld_ac=0; ld_pc=0; wr=0; data_e=0; end
        INST_LOAD  : begin sel=1; rd=1; ld_ir=1; halt=0; inc_pc=0; ld_ac=0; ld_pc=0; wr=0; data_e=0; end
        IDLE       : begin sel=1; rd=1; ld_ir=1; halt=0; inc_pc=0; ld_ac=0; ld_pc=0; wr=0; data_e=0; end
        OP_ADDR    : begin sel=0; rd=0; ld_ir=0; halt=INTER_HALT; inc_pc=1; ld_ac=0; ld_pc=0; wr=0; data_e=0; end
        OP_FETCH   : begin sel=0; rd=INTER_ALUOP; ld_ir=0; halt=0; inc_pc=0; ld_ac=0; ld_pc=0; wr=0; data_e=0; end
        ALU_OP     : begin sel=0; rd=INTER_ALUOP; ld_ir=0; halt=0; inc_pc=INTER_SKZ; ld_ac=0; ld_pc=INTER_JMP; wr=0; data_e=INTER_STO; end
        STORE      : begin sel=0; rd=INTER_ALUOP; ld_ir=0; halt=0; inc_pc=0; ld_ac=INTER_ALUOP; ld_pc=INTER_JMP; wr=INTER_STO; data_e=INTER_STO; end
      endcase
    end
endmodule

lab6-ctrl/controller_test.v
`include "controller.v"

module controller_test;

  localparam integer HLT=0, SKZ=1, ADD=2, AND=3, XOR=4, LDA=5, STO=6, JMP=7;

  reg  [2:0] opcode ;
  reg  [2:0] phase  ;
  reg        zero   ; // accumulator is zero
  wire       sel    ; // select instruction address to memory
  wire       rd     ; // enable memory output onto data bus
  wire       ld_ir  ; // load instruction register
  wire       inc_pc ; // increment program counter
  wire       halt   ; // halt machine
  wire       ld_pc  ; // load program counter
  wire       data_e ; // enable accumulator output onto data bus
  wire       ld_ac  ; // load accumulator from data bus
  wire       wr     ; // write data bus to memory

  controller controller_inst
  (
    .opcode ( opcode ),
    .phase  ( phase  ),
    .zero   ( zero   ),
    .sel    ( sel    ),
    .rd     ( rd     ),
    .ld_ir  ( ld_ir  ),
    .inc_pc ( inc_pc ),
    .halt   ( halt   ),
    .ld_pc  ( ld_pc  ),
    .data_e ( data_e ),
    .ld_ac  ( ld_ac  ),
    .wr     ( wr     ) 
  );

  task expect;
    input [8:0] exp_out;
    if ({sel,rd,ld_ir,inc_pc,halt,ld_pc,data_e,ld_ac,wr} !== exp_out) begin
      $display("\nTEST FAILED");
      $display("time\topcode phase zero sel rd ld_ir inc_pc halt ld_pc data_e ld_ac wr");
      $display("====\t====== ===== ==== === == ===== ====== ==== ===== ====== ===== ==");
      $display("%0d\t%d      %d     %b    %b   %b  %b     %b      %b    %b     %b      %b     %b",
               $time, opcode, phase, zero, sel, rd, ld_ir, inc_pc, halt, ld_pc,
               data_e, ld_ac, wr);
      $display("WANT\t                  %b   %b  %b     %b      %b    %b     %b      %b     %b",
               exp_out[8],exp_out[7],exp_out[6],exp_out[5],exp_out[4],exp_out[3],exp_out[2],exp_out[1],exp_out[0]);
      $finish;
    end
  endtask

  initial begin
    $dumpfile("controller_test.vcd");
    $dumpvars(0, controller_test);
    
    zero=0;

    $write("Testing opcode HLT phase"); opcode=HLT;
    $write(" 0"); phase=0; #1 expect (9'b100000000); // sel
    $write(" 1"); phase=1; #1 expect (9'b110000000); // sel, rd
    $write(" 2"); phase=2; #1 expect (9'b111000000); // sel, rd, ld_ir
    $write(" 3"); phase=3; #1 expect (9'b111000000); // sel, rd, ld_ir
    $write(" 4"); phase=4; #1 expect (9'b000110000); // inc_pc, halt
    $write(" 5"); phase=5; #1 expect (9'b000000000); //
    $write(" 6"); phase=6; #1 expect (9'b000000000); //
    $write(" 7"); phase=7; #1 expect (9'b000000000); //
    $write("\n");

    $write("Testing opcode SKZ phase"); opcode=SKZ;
    $write(" 0"); phase=0; #1 expect (9'b100000000); // sel
    $write(" 1"); phase=1; #1 expect (9'b110000000); // sel, rd
    $write(" 2"); phase=2; #1 expect (9'b111000000); // sel, rd, ld_ir
    $write(" 3"); phase=3; #1 expect (9'b111000000); // sel, rd, ld_ir
    $write(" 4"); phase=4; #1 expect (9'b000100000); // inc_pc
    $write(" 5"); phase=5; #1 expect (9'b000000000); //
    $write(" 6"); phase=6; #1 expect (9'b000000000); //
                  zero=1;  #1 expect (9'b000100000); // inc_pc
    $write(" 7"); phase=7; #1 expect (9'b000000000); //
    $write("\n");

    $write("Testing opcode ADD phase"); opcode=ADD;
    $write(" 0"); phase=0; #1 expect (9'b100000000); // sel
    $write(" 1"); phase=1; #1 expect (9'b110000000); // sel, rd
    $write(" 2"); phase=2; #1 expect (9'b111000000); // sel, rd, ld_ir
    $write(" 3"); phase=3; #1 expect (9'b111000000); // sel, rd, ld_ir
    $write(" 4"); phase=4; #1 expect (9'b000100000); // inc_pc
    $write(" 5"); phase=5; #1 expect (9'b010000000); // rd
    $write(" 6"); phase=6; #1 expect (9'b010000000); // rd
    $write(" 7"); phase=7; #1 expect (9'b010000010); // rd, ld_ac
    $write("\n");

    $write("Testing opcode AND phase"); opcode=AND;
    $write(" 0"); phase=0; #1 expect (9'b100000000); // sel
    $write(" 1"); phase=1; #1 expect (9'b110000000); // sel, rd
    $write(" 2"); phase=2; #1 expect (9'b111000000); // sel, rd, ld_ir
    $write(" 3"); phase=3; #1 expect (9'b111000000); // sel, rd, ld_ir
    $write(" 4"); phase=4; #1 expect (9'b000100000); // inc_pc
    $write(" 5"); phase=5; #1 expect (9'b010000000); // rd
    $write(" 6"); phase=6; #1 expect (9'b010000000); // rd
    $write(" 7"); phase=7; #1 expect (9'b010000010); // rd, ld_ac
    $write("\n");

    $write("Testing opcode XOR phase"); opcode=XOR;
    $write(" 0"); phase=0; #1 expect (9'b100000000); // sel
    $write(" 1"); phase=1; #1 expect (9'b110000000); // sel, rd
    $write(" 2"); phase=2; #1 expect (9'b111000000); // sel, rd, ld_ir
    $write(" 3"); phase=3; #1 expect (9'b111000000); // sel, rd, ld_ir
    $write(" 4"); phase=4; #1 expect (9'b000100000); // inc_pc
    $write(" 5"); phase=5; #1 expect (9'b010000000); // rd
    $write(" 6"); phase=6; #1 expect (9'b010000000); // rd
    $write(" 7"); phase=7; #1 expect (9'b010000010); // rd, ld_ac
    $write("\n");

    $write("Testing opcode LDA phase"); opcode=LDA;
    $write(" 0"); phase=0; #1 expect (9'b100000000); // sel
    $write(" 1"); phase=1; #1 expect (9'b110000000); // sel, rd
    $write(" 2"); phase=2; #1 expect (9'b111000000); // sel, rd, ld_ir
    $write(" 3"); phase=3; #1 expect (9'b111000000); // sel, rd, ld_ir
    $write(" 4"); phase=4; #1 expect (9'b000100000); // inc_pc
    $write(" 5"); phase=5; #1 expect (9'b010000000); // rd
    $write(" 6"); phase=6; #1 expect (9'b010000000); // rd
    $write(" 7"); phase=7; #1 expect (9'b010000010); // rd, ld_ac
    $write("\n");

    $write("Testing opcode STO phase"); opcode=STO;
    $write(" 0"); phase=0; #1 expect (9'b100000000); // sel
    $write(" 1"); phase=1; #1 expect (9'b110000000); // sel, rd
    $write(" 2"); phase=2; #1 expect (9'b111000000); // sel, rd, ld_ir
    $write(" 3"); phase=3; #1 expect (9'b111000000); // sel, rd, ld_ir
    $write(" 4"); phase=4; #1 expect (9'b000100000); // inc_pc
    $write(" 5"); phase=5; #1 expect (9'b000000000); //
    $write(" 6"); phase=6; #1 expect (9'b000000100); // data_e
    $write(" 7"); phase=7; #1 expect (9'b000000101); // data_e, wr
    $write("\n");

    $write("Testing opcode JMP phase"); opcode=JMP;
    $write(" 0"); phase=0; #1 expect (9'b100000000); // sel
    $write(" 1"); phase=1; #1 expect (9'b110000000); // sel, rd
    $write(" 2"); phase=2; #1 expect (9'b111000000); // sel, rd, ld_ir
    $write(" 3"); phase=3; #1 expect (9'b111000000); // sel, rd, ld_ir
    $write(" 4"); phase=4; #1 expect (9'b000100000); // inc_pc
    $write(" 5"); phase=5; #1 expect (9'b000000000); //
    $write(" 6"); phase=6; #1 expect (9'b000001000); // ld_pc
    $write(" 7"); phase=7; #1 expect (9'b000001000); // ld_pc

    $display("\nTEST PASSED");
    $finish;
  end

endmodule

lab6-ctrl/controller_test.vcd
$date
	Sun Mar 17 19:37:20 2024
$end
$version
	Icarus Verilog
$end
$timescale
	1s
$end
$scope module controller_test $end
$var wire 1 ! wr $end
$var wire 1 " sel $end
$var wire 1 # rd $end
$var wire 1 $ ld_pc $end
$var wire 1 % ld_ir $end
$var wire 1 & ld_ac $end
$var wire 1 ' inc_pc $end
$var wire 1 ( halt $end
$var wire 1 ) data_e $end
$var parameter 32 * ADD $end
$var parameter 32 + AND $end
$var parameter 32 , HLT $end
$var parameter 32 - JMP $end
$var parameter 32 . LDA $end
$var parameter 32 / SKZ $end
$var parameter 32 0 STO $end
$var parameter 32 1 XOR $end
$var reg 3 2 opcode [2:0] $end
$var reg 3 3 phase [2:0] $end
$var reg 1 4 zero $end
$scope module controller_inst $end
$var wire 3 5 opcode [2:0] $end
$var wire 3 6 phase [2:0] $end
$var wire 1 4 zero $end
$var parameter 32 7 ADD $end
$var parameter 32 8 ALU_OP $end
$var parameter 32 9 AND $end
$var parameter 32 : HLT $end
$var parameter 32 ; IDLE $end
$var parameter 32 < INST_ADDR $end
$var parameter 32 = INST_FETCH $end
$var parameter 32 > INST_LOAD $end
$var parameter 32 ? JMP $end
$var parameter 32 @ LDA $end
$var parameter 32 A OP_ADDR $end
$var parameter 32 B OP_FETCH $end
$var parameter 32 C SKZ $end
$var parameter 32 D STO $end
$var parameter 32 E STORE $end
$var parameter 32 F XOR $end
$var reg 1 G INTER_ALUOP $end
$var reg 1 H INTER_HALT $end
$var reg 1 I INTER_JMP $end
$var reg 1 J INTER_SKZ $end
$var reg 1 K INTER_STO $end
$var reg 1 ) data_e $end
$var reg 1 ( halt $end
$var reg 1 ' inc_pc $end
$var reg 1 & ld_ac $end
$var reg 1 % ld_ir $end
$var reg 1 $ ld_pc $end
$var reg 1 # rd $end
$var reg 1 " sel $end
$var reg 1 ! wr $end
$upscope $end
$scope task expect $end
$var reg 9 L exp_out [8:0] $end
$upscope $end
$upscope $end
$enddefinitions $end
$comment Show the parameter values. $end
$dumpall
b100 F
b111 E
b110 D
b1 C
b101 B
b100 A
b101 @
b111 ?
b10 >
b1 =
b0 <
b11 ;
b0 :
b11 9
b110 8
b10 7
b100 1
b110 0
b1 /
b101 .
b111 -
b0 ,
b11 +
b10 *
$end
#0
$dumpvars
bx L
0K
0J
0I
1H
0G
b0 6
b0 5
04
b0 3
b0 2
0)
0(
0'
0&
0%
0$
0#
1"
0!
$end
#1
1#
b1 3
b1 6
b100000000 L
#2
1%
b10 3
b10 6
b110000000 L
#3
b11 3
b11 6
b111000000 L
#4
1'
1(
0%
0#
0"
b100 3
b100 6
#5
0'
0(
b101 3
b101 6
b110000 L
#6
b110 3
b110 6
b0 L
#7
b111 3
b111 6
#8
1"
0H
b0 3
b0 6
b1 2
b1 5
#9
1#
b1 3
b1 6
b100000000 L
#10
1%
b10 3
b10 6
b110000000 L
#11
b11 3
b11 6
b111000000 L
#12
1'
0%
0#
0"
b100 3
b100 6
#13
0'
b101 3
b101 6
b100000 L
#14
b110 3
b110 6
b0 L
#15
1'
1J
14
#16
0'
b111 3
b111 6
b100000 L
#17
1"
0J
1G
b0 3
b0 6
b10 2
b10 5
b0 L
#18
1#
b1 3
b1 6
b100000000 L
#19
1%
b10 3
b10 6
b110000000 L
#20
b11 3
b11 6
b111000000 L
#21
1'
0%
0#
0"
b100 3
b100 6
#22
0'
1#
b101 3
b101 6
b100000 L
#23
b110 3
b110 6
b10000000 L
#24
1&
b111 3
b111 6
#25
0&
0#
1"
b0 3
b0 6
b11 2
b11 5
b10000010 L
#26
1#
b1 3
b1 6
b100000000 L
#27
1%
b10 3
b10 6
b110000000 L
#28
b11 3
b11 6
b111000000 L
#29
1'
0%
0#
0"
b100 3
b100 6
#30
0'
1#
b101 3
b101 6
b100000 L
#31
b110 3
b110 6
b10000000 L
#32
1&
b111 3
b111 6
#33
0&
0#
1"
b0 3
b0 6
b100 2
b100 5
b10000010 L
#34
1#
b1 3
b1 6
b100000000 L
#35
1%
b10 3
b10 6
b110000000 L
#36
b11 3
b11 6
b111000000 L
#37
1'
0%
0#
0"
b100 3
b100 6
#38
0'
1#
b101 3
b101 6
b100000 L
#39
b110 3
b110 6
b10000000 L
#40
1&
b111 3
b111 6
#41
0&
0#
1"
b0 3
b0 6
b101 2
b101 5
b10000010 L
#42
1#
b1 3
b1 6
b100000000 L
#43
1%
b10 3
b10 6
b110000000 L
#44
b11 3
b11 6
b111000000 L
#45
1'
0%
0#
0"
b100 3
b100 6
#46
0'
1#
b101 3
b101 6
b100000 L
#47
b110 3
b110 6
b10000000 L
#48
1&
b111 3
b111 6
#49
0&
0#
1"
1K
0G
b0 3
b0 6
b110 2
b110 5
b10000010 L
#50
1#
b1 3
b1 6
b100000000 L
#51
1%
b10 3
b10 6
b110000000 L
#52
b11 3
b11 6
b111000000 L
#53
1'
0%
0#
0"
b100 3
b100 6
#54
0'
b101 3
b101 6
b100000 L
#55
1)
b110 3
b110 6
b0 L
#56
1!
b111 3
b111 6
b100 L
#57
0)
0!
1"
0K
1I
b0 3
b0 6
b111 2
b111 5
b101 L
#58
1#
b1 3
b1 6
b100000000 L
#59
1%
b10 3
b10 6
b110000000 L
#60
b11 3
b11 6
b111000000 L
#61
1'
0%
0#
0"
b100 3
b100 6
#62
0'
b101 3
b101 6
b100000 L
#63
1$
b110 3
b110 6
b0 L
#64
b111 3
b111 6
b1000 L
