lab5-alu/alu.v
module alu
#(
  parameter WIDTH = 8
 )
 (
  input  wire [WIDTH-1:0] in_a,
  input  wire [WIDTH-1:0] in_b,
  input  wire [      2:0] opcode,
  output reg  [WIDTH-1:0] alu_out,
  output reg             a_is_zero
 );
 
  localparam ADD=2, AND=3, XOR=4, PASSB=5;

  always @*
    begin
      a_is_zero = (in_a == 0);
      if ( opcode == ADD )   alu_out = in_a + in_b; else
      if ( opcode == AND )   alu_out = in_a & in_b; else
      if ( opcode == XOR )   alu_out = in_a ^ in_b; else
      if ( opcode == PASSB ) alu_out = in_b;        else
                             alu_out = in_a;
    end

endmodule

lab5-alu/alu_test.v


module alu_test;

  localparam WIDTH=8;

  localparam PASS0=0, PASS1=1, ADD=2, AND=3, XOR=4, PASSB=5, PASS6=6, PASS7=7;

  reg  [      2:0] opcode    ;
  reg  [WIDTH-1:0] in_a      ;
  reg  [WIDTH-1:0] in_b      ;
  wire             a_is_zero ;
  wire [WIDTH-1:0] alu_out   ;


  alu
  #(
    .WIDTH ( WIDTH )
   )
  alu_inst
   (
    .opcode    ( opcode    ),
    .in_a      ( in_a      ),
    .in_b      ( in_b      ),
    .a_is_zero ( a_is_zero ),
    .alu_out   ( alu_out   ) 
   );

  task expect;
    input             exp_zero;
    input [WIDTH-1:0] exp_out;
    if (a_is_zero !== exp_zero || alu_out !== exp_out) begin
      $display("TEST FAILED");
      $display("At time %0d opcode=%b in_a=%b in_b=%b a_is_zero=%b alu_out=%b",
               $time, opcode, in_a, in_b, a_is_zero, alu_out);
      if (a_is_zero !== exp_zero)
        $display("a_is_zero should be %b", exp_zero);
      if (alu_out !== exp_out)
        $display("alu_out should be %b", exp_out);
      $finish;
    end
   else begin
     $display("At time %0d opcode=%b in_a=%b in_b=%b a_is_zero=%b alu_out=%b",
               $time, opcode, in_a, in_b, a_is_zero, alu_out);
   end
  endtask

  initial begin
    $dumpfile("alu_test.vcd");
    $dumpvars(0, alu_test);
    opcode=PASS0; in_a=8'h42; in_b=8'h86; #1 expect (1'b0, 8'h42);
    opcode=PASS1; in_a=8'h42; in_b=8'h86; #1 expect (1'b0, 8'h42);
    opcode=ADD;   in_a=8'h42; in_b=8'h86; #1 expect (1'b0, 8'hC8);
    opcode=AND;   in_a=8'h42; in_b=8'h86; #1 expect (1'b0, 8'h02);
    opcode=XOR;   in_a=8'h42; in_b=8'h86; #1 expect (1'b0, 8'hC4);
    opcode=PASSB; in_a=8'h42; in_b=8'h86; #1 expect (1'b0, 8'h86);
    opcode=PASS6; in_a=8'h42; in_b=8'h86; #1 expect (1'b0, 8'h42);
    opcode=PASS7; in_a=8'h42; in_b=8'h86; #1 expect (1'b0, 8'h42);
    opcode=PASS7; in_a=8'h00; in_b=8'h86; #1 expect (1'b1, 8'h00);
    $display("TEST PASSED");
    $finish;
  end


endmodule

lab5-alu/alu_test.vcd
$date
	Wed May  1 10:04:15 2024
$end
$version
	Icarus Verilog
$end
$timescale
	1s
$end
$scope module alu_test $end
$var wire 8 ! alu_out [7:0] $end
$var wire 1 " a_is_zero $end
$var reg 8 # in_a [7:0] $end
$var reg 8 $ in_b [7:0] $end
$var reg 3 % opcode [2:0] $end
$scope module alu_inst $end
$var wire 8 & in_a [7:0] $end
$var wire 8 ' in_b [7:0] $end
$var wire 3 ( opcode [2:0] $end
$var reg 1 " a_is_zero $end
$var reg 8 ) alu_out [7:0] $end
$upscope $end
$scope task expect $end
$var reg 8 * exp_out [7:0] $end
$var reg 1 + exp_zero $end
$upscope $end
$upscope $end
$enddefinitions $end
#0
$dumpvars
x+
bx *
b1000010 )
b0 (
b10000110 '
b1000010 &
b0 %
b10000110 $
b1000010 #
0"
b1000010 !
$end
#1
b1 %
b1 (
b1000010 *
0+
#2
b11001000 !
b11001000 )
b10 %
b10 (
#3
b10 !
b10 )
b11 %
b11 (
b11001000 *
#4
b11000100 !
b11000100 )
b100 %
b100 (
b10 *
#5
b10000110 !
b10000110 )
b101 %
b101 (
b11000100 *
#6
b1000010 !
b1000010 )
b110 %
b110 (
b10000110 *
#7
b111 %
b111 (
b1000010 *
#8
b0 !
b0 )
1"
b0 #
b0 &
#9
b0 *
1+
